grad_desc_utils/__init__.py
grad_desc_utils-0.0.1.dist-info/LICENSE
grad_desc_utils-0.0.1.dist-info/METADATA
grad_desc_utils-0.0.1.dist-info/WHEEL
grad_desc_utils-0.0.1.dist-info/top_level.txt
grad_desc_utils-0.0.1.dist-info/RECORD
